ProxyEater/Proxy.py
ProxyEater/Scraper.py
ProxyEater/__init__.py
ProxyEater/__main__.py
ProxyEater/sources.json
ProxyEater-1.3.0.dist-info/LICENSE
ProxyEater-1.3.0.dist-info/METADATA
ProxyEater-1.3.0.dist-info/WHEEL
ProxyEater-1.3.0.dist-info/entry_points.txt
ProxyEater-1.3.0.dist-info/top_level.txt
ProxyEater-1.3.0.dist-info/RECORD
