Metadata-Version: 2.1
Name: ProxyEater
Version: 1.3.0
Summary: A Python Proxy Scraper for gathering fresh proxies.
Home-page: https://github.com/MPCodeWriter21/ProxyEater
Author: CodeWriter21
Author-email: CodeWriter21@gmail.com
License: UNKNOWN
Platform: UNKNOWN
Classifier: Programming Language :: Python :: 3
License-File: LICENSE
Requires-Dist: requests
Requires-Dist: beautifulsoup4
Requires-Dist: lxml
Requires-Dist: pandas
Requires-Dist: html5lib
Requires-Dist: log21
Requires-Dist: importlib-resources
